pktron/__init__.py
pktron/algorithms.py
pktron/backend.py
pktron/gates.py
pktron/ml_visualization.py
pktron/quantum.py
pktron/visualization.py
pktron-0.1.6.dist-info/METADATA
pktron-0.1.6.dist-info/WHEEL
pktron-0.1.6.dist-info/top_level.txt
pktron-0.1.6.dist-info/RECORD
