Metadata-Version: 2.4
Name: pktron
Version: 0.1.6
Summary: PKTron Pakistan's 1st Quantum Simulator with 100 Qubits Version 0.1.6
Home-page: https://github.com/pktron/pktron
Author: PKTron Developer Canada
Author-email: info@thecetqap.com
Classifier: Programming Language :: Python :: 3
Classifier: License :: OSI Approved :: MIT License
Classifier: Operating System :: OS Independent
Requires-Python: >=3.7
Requires-Dist: numpy>=1.21.0
Requires-Dist: pennylane>=0.38.0
Requires-Dist: matplotlib>=3.4.0
Requires-Dist: quimb>=1.4.0
Requires-Dist: networkx>=2.8.0
Requires-Dist: plotly>=5.0.0
Requires-Dist: seaborn>=0.11.0
Requires-Dist: qutip>=4.6.0
Requires-Dist: imageio>=2.9.0
Dynamic: author
Dynamic: author-email
Dynamic: classifier
Dynamic: description
Dynamic: description-content-type
Dynamic: home-page
Dynamic: requires-dist
Dynamic: requires-python
Dynamic: summary
